[
  {
    "name": "МАУ «Парки Самары»",
    "location": "443010, г. Самара, ул. Красноармейская, 2",
    "phoneNumber": "+7 (846) 332-11-63"
  },
  {
    "name": "МКУ «Самарский бизнес - инкубатор»",
    "location": "г. Самара, Куйбышевский район, ул. Главная, 3",
    "phoneNumber": "+7 (846) 207 68 60",
    "email": "info@samarabiznes.ru"
  },
  {
    "name": "МП «Самарагорсвет»",
    "location": "443020, г. Самара, ул. Галактионовская, 9",
    "phoneNumber": "+7 (846) 333-33-62",
    "email": "Samaragorsvet@mail.ru"
  },
  {
    "name": "МП «Архитектурно-планировочное бюро»",
    "location": "443100, г. Самара, ул. Первомайская, 21",
    "phoneNumber": "+7 (846) 242-40-67",
    "email": "mpapb@mail.ru"
  },
  {
    "name": "МАУ «Самарская Газета»",
    "location": "443020, г.Самара, ул. Галактионовская, 39",
    "phoneNumber": "+7 (846) 979-75-80"
  }
]